my_module229.cpython-313-x86_64-linux-gnu.so
my_module229-0.1.0.dist-info/METADATA
my_module229-0.1.0.dist-info/WHEEL
my_module229-0.1.0.dist-info/top_level.txt
my_module229-0.1.0.dist-info/RECORD
